aio_odoorpc/__init__.py
aio_odoorpc/aio_odoorpc.py
aio_odoorpc/helpers.py
aio_odoorpc/odoorpc.py
aio_odoorpc-2.0.0.dist-info/LICENSE.txt
aio_odoorpc-2.0.0.dist-info/WHEEL
aio_odoorpc-2.0.0.dist-info/METADATA
aio_odoorpc-2.0.0.dist-info/RECORD
