Metadata-Version: 2.1
Name: aio-odoorpc
Version: 2.0.0
Summary: Fast, simple Odoo RPC client with both synchronous and an asynchronous API
Home-page: https://github.com/mbello/aio-odoorpc
License: MIT
Keywords: odoorpc,asyncio,jsonrpc,odoo,ERPpeek
Author: mbello
Author-email: mbello@users.noreply.github.com
Requires-Python: >=3.6
Classifier: License :: OSI Approved :: MIT License
Classifier: Programming Language :: Python :: 3
Classifier: Programming Language :: Python :: 3.6
Classifier: Programming Language :: Python :: 3.7
Classifier: Programming Language :: Python :: 3.8
Classifier: Programming Language :: Python :: 3.9
Requires-Dist: aio-odoorpc-base (>=3.0.4)
Project-URL: Repository, https://github.com/mbello/aio-odoorpc
